extract_sequences/__init__.py
extract_sequences/__main__.py
extract_sequences/extract_sequences.py
fetch_sequences/__init__.py
fetch_sequences/__main__.py
fetch_sequences/fetch_sequences.py
mlst/__init__.py
mlst/__main__.py
mlst/mlst.py
mlst/mlst_db/INSTALL.py
mlst/mlst_db/UPDATE.py
mlst/mlst_db/VALIDATION.py
utils/__init__.py
utils/__main__.py
utils/utils.py
labscripts-0.1.1.dist-info/LICENSE
labscripts-0.1.1.dist-info/METADATA
labscripts-0.1.1.dist-info/WHEEL
labscripts-0.1.1.dist-info/entry_points.txt
labscripts-0.1.1.dist-info/top_level.txt
labscripts-0.1.1.dist-info/RECORD
